GNUmakefile
INSTALL
LICENSE
MANIFEST.in
NEWS
README.rst
cheat.el
distribute_setup.py
elffile.py
objcmp.py
objdump.py
setup.cfg
setup.py
tests.py
tst.py
elffile.egg-info/PKG-INFO
elffile.egg-info/SOURCES.txt
elffile.egg-info/dependency_links.txt
elffile.egg-info/requires.txt
elffile.egg-info/top_level.txt
testfiles/AUTHORS
testfiles/COPYING
testfiles/ChangeLog
testfiles/INSTALL
testfiles/Makefile.am
testfiles/Makefile.in
testfiles/NEWS
testfiles/README
testfiles/a.c
testfiles/aclocal.m4
testfiles/b.c
testfiles/c.c
testfiles/config.guess
testfiles/config.sub
testfiles/configure
testfiles/configure.ac
testfiles/d.c
testfiles/depcomp
testfiles/dynamic.h
testfiles/e.c
testfiles/f.c
testfiles/hello.c
testfiles/install-sh
testfiles/ltmain.sh
testfiles/missing
testfiles/static.h
testfiles/autom4te.cache/output.0
testfiles/autom4te.cache/output.1
testfiles/autom4te.cache/output.2
testfiles/autom4te.cache/output.3
testfiles/autom4te.cache/requests
testfiles/autom4te.cache/traces.0
testfiles/autom4te.cache/traces.1
testfiles/autom4te.cache/traces.2
testfiles/autom4te.cache/traces.3
testfiles/i686-pc-linux-gnu/a.o
testfiles/i686-pc-linux-gnu/b.o
testfiles/i686-pc-linux-gnu/c.o
testfiles/i686-pc-linux-gnu/d.o
testfiles/i686-pc-linux-gnu/e.o
testfiles/i686-pc-linux-gnu/f.o
testfiles/i686-pc-linux-gnu/hello
testfiles/i686-pc-linux-gnu/hello.o
testfiles/i686-pc-linux-gnu/.libs/a.o
testfiles/i686-pc-linux-gnu/.libs/b.o
testfiles/i686-pc-linux-gnu/.libs/c.o
testfiles/i686-pc-linux-gnu/.libs/d.o
testfiles/i686-pc-linux-gnu/.libs/e.o
testfiles/i686-pc-linux-gnu/.libs/f.o
testfiles/i686-pc-linux-gnu/.libs/hello
testfiles/i686-pc-linux-gnu/.libs/libdynamic.a
testfiles/i686-pc-linux-gnu/.libs/libdynamic.so
testfiles/i686-pc-linux-gnu/.libs/libdynamic.so.0
testfiles/i686-pc-linux-gnu/.libs/libdynamic.so.0.0.0
testfiles/i686-pc-linux-gnu/.libs/libstatic.a
testfiles/i686-pc-linux-gnu/.libs/libstatic.so
testfiles/i686-pc-linux-gnu/.libs/libstatic.so.0
testfiles/i686-pc-linux-gnu/.libs/libstatic.so.0.0.0
testfiles/x86_64-unknown-linux-gnu/Makefile
testfiles/x86_64-unknown-linux-gnu/a.lo
testfiles/x86_64-unknown-linux-gnu/a.o
